Metadata-Version: 2.1
Name: donk.ai
Version: 0.1.0
Summary: Reinforcement Learning Toolbox
Home-page: https://github.com/DiddiZ/donk.ai
Author: Robin Kupper
Author-email: robin.kupper@diddiz.de
License: UNKNOWN
Project-URL: Bug Reports, https://github.com/DiddiZ/donk.ai/issues
Project-URL: Source, https://github.com/DiddiZ/donk.ai
Keywords: learning machine reinforcement
Platform: UNKNOWN
Classifier: Development Status :: 3 - Alpha
Classifier: Intended Audience :: Developers
Classifier: License :: OSI Approved :: MIT License
Classifier: Programming Language :: Python :: 3
Classifier: Programming Language :: Python :: 3.8
Classifier: Programming Language :: Python :: 3.9
Requires-Python: >=3.8, <4
License-File: LICENSE
Requires-Dist: numpy (~=1.21)
Requires-Dist: scipy (~=1.7.0)
Requires-Dist: scikit-learn (~=0.24.2)
Requires-Dist: matplotlib (~=3.4.2)
Requires-Dist: seaborn (~=0.11.1)
Requires-Dist: pandas (~=1.3.1)
Requires-Dist: tensorflow (~=2.8.0)
Requires-Dist: tensorflow-probability (~=0.15.0)
Requires-Dist: keras (~=2.8.0)
Requires-Dist: sympy (~=1.9)
Requires-Dist: tqdm
Provides-Extra: dev
